<?xml version="1.0" encoding="utf-8" standalone="yes"?><set name="March of the Machine Collector Boosters" id="7A734F02-D5E4-4DD0-A6D7-7EAC948B51FB" gameId="A6C8D2E8-7CD8-11DD-8F94-E62B56D89593" gameVersion="2.0.4" version="3.1"><packaging></packaging><cards><card id="f95a91a9-e0e2-41db-a52b-9345ee6025f2" name="Elesh Norn"><property name="Cost" value="{2}{W}{W}"/><property name="Converted Mana Cost" value="4"/><property name="Color" value="White"/><property name="Type" value="Legendary Creature"/><property name="Subtype" value="Phyrexian Praetor"/><property name="Rarity" value="Mythic Rare"/><property name="Rules" value="Vigilance&#xD;&#xA;Whenever a source an opponent controls deals damage to you or a permanent you control, that source's controller loses 2 life unless they pay {1}.&#xD;&#xA;{2}{W}, Sacrifice three other creatures: Exile Elesh Norn, then return it to the battlefield transformed under its owner's control. Activate only as a sorcery."/><property name="Flavor" value=""/><property name="Power" value="3"/><property name="Toughness" value="5"/><property name="PT Box" value="3 / 5"/><property name="Artist" value="Kekai Kotaki"/><property name="MultiverseId" value="SF-MOM_292a"/><property name="Number" value="292"/></card><card id="f66dcfb6-3072-435e-af44-3fda9966a63e" name="The Argent Etchings"><property name="Cost" value=""/><property name="Converted Mana Cost" value="4"/><property name="Color" value="White"/><property name="Type" value="Enchantment"/><property name="Subtype" value="Saga"/><property name="Rarity" value="Mythic Rare"/><property name="Rules" value="(As this Saga enters and after your draw step, add a lore counter.)&#xD;&#xA;I - Incubate 2 five times, then transform all Incubator tokens you control.&#xD;&#xA;II - Creatures you control get +1/+1 and gain double strike until end of turn.&#xD;&#xA;III - Destroy all other permanents except for artifacts, lands, and Phyrexians. Exile The Argent Etchings, then return it to the battlefield (front face up)."/><property name="Flavor" value=""/><property name="Power" value=""/><property name="Toughness" value=""/><property name="PT Box" value=""/><property name="Artist" value="Kekai Kotaki"/><property name="MultiverseId" value="SF-MOM_292b"/><property name="Number" value="292"/></card><card id="dcb5b7b9-b437-433b-b03c-5ad8eebe666b" name="Heliod, the Radiant Dawn"><property name="Cost" value="{2}{W}{W}"/><property name="Converted Mana Cost" value="4"/><property name="Color" value="White"/><property name="Type" value="Legendary Enchantment Creature"/><property name="Subtype" value="God"/><property name="Rarity" value="Rare"/><property name="Rules" value="When Heliod, the Radiant Dawn enters the battlefield, return target enchantment card that isn't a God from your graveyard to your hand.&#xD;&#xA;{3}{PU}: Transform Heliod, the Radiant Dawn. Activate only as a sorcery. ({PU} can be paid with either {U} or 2 life.)"/><property name="Flavor" value=""/><property name="Power" value="4"/><property name="Toughness" value="4"/><property name="PT Box" value="4 / 4"/><property name="Artist" value="Jason A. Engle"/><property name="MultiverseId" value="SF-MOM_293a"/><property name="Number" value="293"/></card><card id="4b54784c-feda-460d-8b26-a07ff8d35255" name="Heliod, the Warped Eclipse"><property name="Cost" value=""/><property name="Converted Mana Cost" value="4"/><property name="Color" value="Multicolor White Blue"/><property name="Type" value="Legendary Enchantment Creature"/><property name="Subtype" value="Phyrexian God"/><property name="Rarity" value="Rare"/><property name="Rules" value="You may cast spells as though they had flash.&#xD;&#xA;Spells you cast cost {1} less to cast for each card your opponents have drawn this turn."/><property name="Flavor" value=""/><property name="Power" value="4"/><property name="Toughness" value="6"/><property name="PT Box" value="4 / 6"/><property name="Artist" value="Jason A. Engle"/><property name="MultiverseId" value="SF-MOM_293b"/><property name="Number" value="293"/></card><card id="0888e2f1-0fe4-470a-9c36-100e4b2a109d" name="Jin-Gitaxias"><property name="Cost" value="{3}{U}{U}"/><property name="Converted Mana Cost" value="5"/><property name="Color" value="Blue"/><property name="Type" value="Legendary Creature"/><property name="Subtype" value="Phyrexian Praetor"/><property name="Rarity" value="Mythic Rare"/><property name="Rules" value="Ward {2}&#xD;&#xA;Whenever you cast a noncreature spell with mana value 3 or greater, draw a card.&#xD;&#xA;{3}{U}: Exile Jin-Gitaxias, then return it to the battlefield transformed under its owner's control. Activate only as a sorcery and only if you have seven or more cards in hand."/><property name="Flavor" value=""/><property name="Power" value="5"/><property name="Toughness" value="5"/><property name="PT Box" value="5 / 5"/><property name="Artist" value="Dominik Mayer"/><property name="MultiverseId" value="SF-MOM_294a"/><property name="Number" value="294"/></card><card id="e17b53cc-1457-43c2-b1da-7232199c9610" name="The Great Synthesis"><property name="Cost" value=""/><property name="Converted Mana Cost" value="5"/><property name="Color" value="Blue"/><property name="Type" value="Enchantment"/><property name="Subtype" value="Saga"/><property name="Rarity" value="Mythic Rare"/><property name="Rules" value="(As this Saga enters and after your draw step, add a lore counter.)&#xD;&#xA;I - Draw cards equal to the number of cards in your hand. You have no maximum hand size for as long as you control The Great Synthesis.&#xD;&#xA;II - Return all non-Phyrexian creatures to their owners' hands.&#xD;&#xA;III - You may cast any number of spells from your hand without paying their mana costs. Exile The Great Synthesis, then return it to the battlefield (front face up)."/><property name="Flavor" value=""/><property name="Power" value=""/><property name="Toughness" value=""/><property name="PT Box" value=""/><property name="Artist" value="Dominik Mayer"/><property name="MultiverseId" value="SF-MOM_294b"/><property name="Number" value="294"/></card><card id="67d22ca9-bff9-414a-a66b-611aec78b909" name="Rona, Herald of Invasion"><property name="Cost" value="{1}{U}"/><property name="Converted Mana Cost" value="2"/><property name="Color" value="Blue"/><property name="Type" value="Legendary Creature"/><property name="Subtype" value="Human Wizard"/><property name="Rarity" value="Rare"/><property name="Rules" value="Whenever you cast a legendary spell, untap Rona, Herald of Invasion.&#xD;&#xA;{T}: Draw a card, then discard a card.&#xD;&#xA;{5}{PB}: Transform Rona. Activate only as a sorcery. ({PB} can be paid with either {B} or 2 life.)"/><property name="Flavor" value=""/><property name="Power" value="1"/><property name="Toughness" value="3"/><property name="PT Box" value="1 / 3"/><property name="Artist" value="Daniel Lieske"/><property name="MultiverseId" value="SF-MOM_295a"/><property name="Number" value="295"/></card><card id="bb8417f3-8b43-4bfe-ad9f-8f75da9eaca6" name="Rona, Tolarian Obliterator"><property name="Cost" value=""/><property name="Converted Mana Cost" value="2"/><property name="Color" value="Multicolor Blue Black"/><property name="Type" value="Legendary Creature"/><property name="Subtype" value="Phyrexian Wizard"/><property name="Rarity" value="Rare"/><property name="Rules" value="Trample&#xD;&#xA;Whenever a source deals damage to Rona, Tolarian Obliterator, that source's controller exiles a card from their hand at random. If it's a land card, you may put it onto the battlefield under your control. Otherwise, you may cast it without paying its mana cost."/><property name="Flavor" value=""/><property name="Power" value="5"/><property name="Toughness" value="5"/><property name="PT Box" value="5 / 5"/><property name="Artist" value="Daniel Lieske"/><property name="MultiverseId" value="SF-MOM_295b"/><property name="Number" value="295"/></card><card id="289219cc-1141-4587-9dec-09928e21fd64" name="Ayara, Widow of the Realm"><property name="Cost" value="{1}{B}{B}"/><property name="Converted Mana Cost" value="3"/><property name="Color" value="Black"/><property name="Type" value="Legendary Creature"/><property name="Subtype" value="Elf Noble"/><property name="Rarity" value="Rare"/><property name="Rules" value="{T}, Sacrifice another creature or artifact: Ayara, Widow of the Realm deals X damage to target opponent or battle and you gain X life, where X is the sacrificed permanent's mana value.&#xD;&#xA;{5}{PR}: Transform Ayara. Activate only as a sorcery. ({PR} can be paid with either {R} or 2 life.)"/><property name="Flavor" value=""/><property name="Power" value="3"/><property name="Toughness" value="3"/><property name="PT Box" value="3 / 3"/><property name="Artist" value="Josu Hernaiz"/><property name="MultiverseId" value="SF-MOM_296a"/><property name="Number" value="296"/></card><card id="e867cd80-320f-43bb-9192-955671c157c3" name="Ayara, Furnace Queen"><property name="Cost" value=""/><property name="Converted Mana Cost" value="3"/><property name="Color" value="Multicolor Black Red"/><property name="Type" value="Legendary Creature"/><property name="Subtype" value="Phyrexian Elf Noble"/><property name="Rarity" value="Rare"/><property name="Rules" value="At the beginning of combat on your turn, return up to one target artifact or creature card from your graveyard to the battlefield. It gains haste. Exile it at the beginning of the next end step."/><property name="Flavor" value=""/><property name="Power" value="4"/><property name="Toughness" value="4"/><property name="PT Box" value="4 / 4"/><property name="Artist" value="Josu Hernaiz"/><property name="MultiverseId" value="SF-MOM_296b"/><property name="Number" value="296"/></card><card id="fdf6640e-8197-4430-b09e-60c265a1d04c" name="Sheoldred"><property name="Cost" value="{3}{B}{B}"/><property name="Converted Mana Cost" value="5"/><property name="Color" value="Black"/><property name="Type" value="Legendary Creature"/><property name="Subtype" value="Phyrexian Praetor"/><property name="Rarity" value="Mythic Rare"/><property name="Rules" value="Menace&#xD;&#xA;When Sheoldred enters the battlefield, each opponent sacrifices a nontoken creature or planeswalker.&#xD;&#xA;{4}{B}: Exile Sheoldred, then return it to the battlefield transformed under its owner's control. Activate only as a sorcery and only if an opponent has eight or more cards in their graveyard."/><property name="Flavor" value=""/><property name="Power" value="4"/><property name="Toughness" value="5"/><property name="PT Box" value="4 / 5"/><property name="Artist" value="Dominik Mayer"/><property name="MultiverseId" value="SF-MOM_297a"/><property name="Number" value="297"/></card><card id="27bf647a-809b-4277-9a06-3dce4606e653" name="The True Scriptures"><property name="Cost" value=""/><property name="Converted Mana Cost" value="5"/><property name="Color" value="Black"/><property name="Type" value="Enchantment"/><property name="Subtype" value="Saga"/><property name="Rarity" value="Mythic Rare"/><property name="Rules" value="(As this Saga enters and after your draw step, add a lore counter.)&#xD;&#xA;I - For each opponent, destroy up to one target creature or planeswalker that player controls.&#xD;&#xA;II - Each opponent discards three cards, then mills three cards.&#xD;&#xA;III - Put all creature cards from all graveyards onto the battlefield under your control. Exile The True Scriptures, then return it to the battlefield (front face up)."/><property name="Flavor" value=""/><property name="Power" value=""/><property name="Toughness" value=""/><property name="PT Box" value=""/><property name="Artist" value="Dominik Mayer"/><property name="MultiverseId" value="SF-MOM_297b"/><property name="Number" value="297"/></card><card id="09eff6cd-b5a0-4696-b5b7-af09123d4084" name="Etali, Primal Conqueror"><property name="Cost" value="{5}{R}{R}"/><property name="Converted Mana Cost" value="7"/><property name="Color" value="Red"/><property name="Type" value="Legendary Creature"/><property name="Subtype" value="Elder Dinosaur"/><property name="Rarity" value="Rare"/><property name="Rules" value="Trample&#xD;&#xA;When Etali, Primal Conqueror enters the battlefield, each player exiles cards from the top of their library until they exile a nonland card. You may cast any number of spells from among the nonland cards exiled this way without paying their mana costs.&#xD;&#xA;{9}{PG}: Transform Etali. Activate only as a sorcery."/><property name="Flavor" value=""/><property name="Power" value="7"/><property name="Toughness" value="7"/><property name="PT Box" value="7 / 7"/><property name="Artist" value="Yeong-Hao Han"/><property name="MultiverseId" value="SF-MOM_298a"/><property name="Number" value="298"/></card><card id="fa62009d-75c8-4606-968d-4a2988ae7b19" name="Etali, Primal Sickness"><property name="Cost" value=""/><property name="Converted Mana Cost" value="7"/><property name="Color" value="Multicolor Red Green"/><property name="Type" value="Legendary Creature"/><property name="Subtype" value="Phyrexian Elder Dinosaur"/><property name="Rarity" value="Rare"/><property name="Rules" value="Trample, indestructible&#xD;&#xA;Whenever Etali, Primal Sickness deals combat damage to a player, they get that many poison counters. (A player with ten or more poison counters loses the game.)"/><property name="Flavor" value=""/><property name="Power" value="11"/><property name="Toughness" value="11"/><property name="PT Box" value="11 / 11"/><property name="Artist" value="Yeong-Hao Han"/><property name="MultiverseId" value="SF-MOM_298b"/><property name="Number" value="298"/></card><card id="ee6608bc-796b-4338-b2a3-a2acec5dfcb9" name="Urabrask"><property name="Cost" value="{2}{R}{R}"/><property name="Converted Mana Cost" value="4"/><property name="Color" value="Red"/><property name="Type" value="Legendary Creature"/><property name="Subtype" value="Phyrexian Praetor"/><property name="Rarity" value="Mythic Rare"/><property name="Rules" value="First strike&#xD;&#xA;Whenever you cast an instant or sorcery spell, Urabrask deals 1 damage to target opponent. Add {R}.&#xD;&#xA;{R}: Exile Urabrask, then return it to the battlefield transformed under its owner's control. Activate only as a sorcery and only if you've cast three or more instant and/or sorcery spells this turn."/><property name="Flavor" value=""/><property name="Power" value="4"/><property name="Toughness" value="4"/><property name="PT Box" value="4 / 4"/><property name="Artist" value="Kekai Kotaki"/><property name="MultiverseId" value="SF-MOM_299a"/><property name="Number" value="299"/></card><card id="21a7b4b5-ed0f-492c-938a-d229d0770c5d" name="The Great Work"><property name="Cost" value=""/><property name="Converted Mana Cost" value="4"/><property name="Color" value="Red"/><property name="Type" value="Enchantment"/><property name="Subtype" value="Saga"/><property name="Rarity" value="Mythic Rare"/><property name="Rules" value="(As this Saga enters and after your draw step, add a lore counter.)&#xD;&#xA;I - The Great Work deals 3 damage to target opponent and each creature they control.&#xD;&#xA;II - Create three Treasure tokens.&#xD;&#xA;III - Until end of turn, you may cast instant and sorcery spells from any graveyard. If a spell cast this way would be put into a graveyard, exile it instead. Exile The Great Work, then return it to the battlefield (front face up)."/><property name="Flavor" value=""/><property name="Power" value=""/><property name="Toughness" value=""/><property name="PT Box" value=""/><property name="Artist" value="Kekai Kotaki"/><property name="MultiverseId" value="SF-MOM_299b"/><property name="Number" value="299"/></card><card id="b9804fea-2304-4492-b90b-e9d41e66361a" name="Polukranos Reborn"><property name="Cost" value="{G}{G}{G}"/><property name="Converted Mana Cost" value="3"/><property name="Color" value="Green"/><property name="Type" value="Legendary Creature"/><property name="Subtype" value="Hydra"/><property name="Rarity" value="Rare"/><property name="Rules" value="Reach&#xD;&#xA;{6}{PW}: Transform Polukranos Reborn. Activate only as a sorcery. ({PW} can be paid with either {W} or 2 life.)"/><property name="Flavor" value=""/><property name="Power" value="4"/><property name="Toughness" value="5"/><property name="PT Box" value="4 / 5"/><property name="Artist" value="Jason A. Engle"/><property name="MultiverseId" value="SF-MOM_300a"/><property name="Number" value="300"/></card><card id="fba99c9c-5369-40c9-b54a-83611296b264" name="Polukranos, Engine of Ruin"><property name="Cost" value=""/><property name="Converted Mana Cost" value="3"/><property name="Color" value="Multicolor White Green"/><property name="Type" value="Legendary Creature"/><property name="Subtype" value="Phyrexian Hydra"/><property name="Rarity" value="Rare"/><property name="Rules" value="Reach, lifelink&#xD;&#xA;Whenever Polukranos, Engine of Ruin or another nontoken Hydra you control dies, create a 3/3 green and white Phyrexian Hydra creature token with reach and a 3/3 green and white Phyrexian Hydra creature token with lifelink."/><property name="Flavor" value=""/><property name="Power" value="6"/><property name="Toughness" value="6"/><property name="PT Box" value="6 / 6"/><property name="Artist" value="Jason A. Engle"/><property name="MultiverseId" value="SF-MOM_300b"/><property name="Number" value="300"/></card><card id="228a15fb-69f7-43af-b703-ab8f91aa6b56" name="Vorinclex"><property name="Cost" value="{3}{G}{G}"/><property name="Converted Mana Cost" value="5"/><property name="Color" value="Green"/><property name="Type" value="Legendary Creature"/><property name="Subtype" value="Phyrexian Praetor"/><property name="Rarity" value="Mythic Rare"/><property name="Rules" value="Trample, reach&#xD;&#xA;When Vorinclex enters the battlefield, search your library for up to two Forest cards, reveal them, put them into your hand, then shuffle.&#xD;&#xA;{6}{G}{G}: Exile Vorinclex, then return it to the battlefield transformed under its owner's control. Activate only as a sorcery."/><property name="Flavor" value=""/><property name="Power" value="6"/><property name="Toughness" value="6"/><property name="PT Box" value="6 / 6"/><property name="Artist" value="Flavio Girón"/><property name="MultiverseId" value="SF-MOM_301a"/><property name="Number" value="301"/></card><card id="126befef-af3c-4fd8-88ab-f5aeaed40298" name="The Grand Evolution"><property name="Cost" value=""/><property name="Converted Mana Cost" value="5"/><property name="Color" value="Green"/><property name="Type" value="Enchantment"/><property name="Subtype" value="Saga"/><property name="Rarity" value="Mythic Rare"/><property name="Rules" value="(As this Saga enters and after your draw step, add a lore counter.)&#xD;&#xA;I - Mill ten cards. Put up to two creature cards from among the milled cards onto the battlefield.&#xD;&#xA;II - Distribute seven +1/+1 counters among any number of target creatures you control.&#xD;&#xA;III - Until end of turn, creatures you control gain &quot;{1}: This creature fights target creature you don't control.&quot; Exile The Grand Evolution, then return it to the battlefield (front face up)."/><property name="Flavor" value=""/><property name="Power" value=""/><property name="Toughness" value=""/><property name="PT Box" value=""/><property name="Artist" value="Flavio Girón"/><property name="MultiverseId" value="SF-MOM_301b"/><property name="Number" value="301"/></card><card id="3b451792-040d-495c-881e-54a5e3fb4740" name="Elesh Norn"><property name="Cost" value="{2}{W}{W}"/><property name="Converted Mana Cost" value="4"/><property name="Color" value="White"/><property name="Type" value="Legendary Creature"/><property name="Subtype" value="Phyrexian Praetor"/><property name="Rarity" value="Mythic Rare"/><property name="Rules" value="Vigilance&#xD;&#xA;Whenever a source an opponent controls deals damage to you or a permanent you control, that source's controller loses 2 life unless they pay {1}.&#xD;&#xA;{2}{W}, Sacrifice three other creatures: Exile Elesh Norn, then return it to the battlefield transformed under its owner's control. Activate only as a sorcery."/><property name="Flavor" value=""/><property name="Power" value="3"/><property name="Toughness" value="5"/><property name="PT Box" value="3 / 5"/><property name="Artist" value="Ryan Pancoast"/><property name="MultiverseId" value="SF-MOM_338a"/><property name="Number" value="338"/></card><card id="4e222612-da00-4a00-b07c-c74a51808f2f" name="The Argent Etchings"><property name="Cost" value=""/><property name="Converted Mana Cost" value="4"/><property name="Color" value="White"/><property name="Type" value="Enchantment"/><property name="Subtype" value="Saga"/><property name="Rarity" value="Mythic Rare"/><property name="Rules" value="(As this Saga enters and after your draw step, add a lore counter.)&#xD;&#xA;I - Incubate 2 five times, then transform all Incubator tokens you control.&#xD;&#xA;II - Creatures you control get +1/+1 and gain double strike until end of turn.&#xD;&#xA;III - Destroy all other permanents except for artifacts, lands, and Phyrexians. Exile The Argent Etchings, then return it to the battlefield (front face up)."/><property name="Flavor" value=""/><property name="Power" value=""/><property name="Toughness" value=""/><property name="PT Box" value=""/><property name="Artist" value="Ryan Pancoast"/><property name="MultiverseId" value="SF-MOM_338b"/><property name="Number" value="338"/></card><card id="e4580c04-6222-403b-ac1a-43b55c32bf38" name="Jin-Gitaxias"><property name="Cost" value="{3}{U}{U}"/><property name="Converted Mana Cost" value="5"/><property name="Color" value="Blue"/><property name="Type" value="Legendary Creature"/><property name="Subtype" value="Phyrexian Praetor"/><property name="Rarity" value="Mythic Rare"/><property name="Rules" value="Ward {2}&#xD;&#xA;Whenever you cast a noncreature spell with mana value 3 or greater, draw a card.&#xD;&#xA;{3}{U}: Exile Jin-Gitaxias, then return it to the battlefield transformed under its owner's control. Activate only as a sorcery and only if you have seven or more cards in hand."/><property name="Flavor" value=""/><property name="Power" value="5"/><property name="Toughness" value="5"/><property name="PT Box" value="5 / 5"/><property name="Artist" value="Julian Kok Joon Wen"/><property name="MultiverseId" value="SF-MOM_339a"/><property name="Number" value="339"/></card><card id="da168420-f8d2-479d-985b-909d5ac1019f" name="The Great Synthesis"><property name="Cost" value=""/><property name="Converted Mana Cost" value="5"/><property name="Color" value="Blue"/><property name="Type" value="Enchantment"/><property name="Subtype" value="Saga"/><property name="Rarity" value="Mythic Rare"/><property name="Rules" value="(As this Saga enters and after your draw step, add a lore counter.)&#xD;&#xA;I - Draw cards equal to the number of cards in your hand. You have no maximum hand size for as long as you control The Great Synthesis.&#xD;&#xA;II - Return all non-Phyrexian creatures to their owners' hands.&#xD;&#xA;III - You may cast any number of spells from your hand without paying their mana costs. Exile The Great Synthesis, then return it to the battlefield (front face up)."/><property name="Flavor" value=""/><property name="Power" value=""/><property name="Toughness" value=""/><property name="PT Box" value=""/><property name="Artist" value="Julian Kok Joon Wen"/><property name="MultiverseId" value="SF-MOM_339b"/><property name="Number" value="339"/></card><card id="b573719d-ae59-43d6-be52-24e803f775f0" name="Sheoldred"><property name="Cost" value="{3}{B}{B}"/><property name="Converted Mana Cost" value="5"/><property name="Color" value="Black"/><property name="Type" value="Legendary Creature"/><property name="Subtype" value="Phyrexian Praetor"/><property name="Rarity" value="Mythic Rare"/><property name="Rules" value="Menace&#xD;&#xA;When Sheoldred enters the battlefield, each opponent sacrifices a nontoken creature or planeswalker.&#xD;&#xA;{4}{B}: Exile Sheoldred, then return it to the battlefield transformed under its owner's control. Activate only as a sorcery and only if an opponent has eight or more cards in their graveyard."/><property name="Flavor" value=""/><property name="Power" value="4"/><property name="Toughness" value="5"/><property name="PT Box" value="4 / 5"/><property name="Artist" value="Camille Alquier"/><property name="MultiverseId" value="SF-MOM_340a"/><property name="Number" value="340"/></card><card id="b0471058-dac3-4373-8e2f-0d266654c22a" name="The True Scriptures"><property name="Cost" value=""/><property name="Converted Mana Cost" value="5"/><property name="Color" value="Black"/><property name="Type" value="Enchantment"/><property name="Subtype" value="Saga"/><property name="Rarity" value="Mythic Rare"/><property name="Rules" value="(As this Saga enters and after your draw step, add a lore counter.)&#xD;&#xA;I - For each opponent, destroy up to one target creature or planeswalker that player controls.&#xD;&#xA;II - Each opponent discards three cards, then mills three cards.&#xD;&#xA;III - Put all creature cards from all graveyards onto the battlefield under your control. Exile The True Scriptures, then return it to the battlefield (front face up)."/><property name="Flavor" value=""/><property name="Power" value=""/><property name="Toughness" value=""/><property name="PT Box" value=""/><property name="Artist" value="Camille Alquier"/><property name="MultiverseId" value="SF-MOM_340b"/><property name="Number" value="340"/></card><card id="d3736bd7-ab0a-45e2-8907-dd5a4fc02e93" name="Urabrask"><property name="Cost" value="{2}{R}{R}"/><property name="Converted Mana Cost" value="4"/><property name="Color" value="Red"/><property name="Type" value="Legendary Creature"/><property name="Subtype" value="Phyrexian Praetor"/><property name="Rarity" value="Mythic Rare"/><property name="Rules" value="First strike&#xD;&#xA;Whenever you cast an instant or sorcery spell, Urabrask deals 1 damage to target opponent. Add {R}.&#xD;&#xA;{R}: Exile Urabrask, then return it to the battlefield transformed under its owner's control. Activate only as a sorcery and only if you've cast three or more instant and/or sorcery spells this turn."/><property name="Flavor" value=""/><property name="Power" value="4"/><property name="Toughness" value="4"/><property name="PT Box" value="4 / 4"/><property name="Artist" value="José Parodi"/><property name="MultiverseId" value="SF-MOM_341a"/><property name="Number" value="341"/></card><card id="edc14f1d-91e6-492a-bf47-2f4de9bc7b7b" name="The Great Work"><property name="Cost" value=""/><property name="Converted Mana Cost" value="4"/><property name="Color" value="Red"/><property name="Type" value="Enchantment"/><property name="Subtype" value="Saga"/><property name="Rarity" value="Mythic Rare"/><property name="Rules" value="(As this Saga enters and after your draw step, add a lore counter.)&#xD;&#xA;I - The Great Work deals 3 damage to target opponent and each creature they control.&#xD;&#xA;II - Create three Treasure tokens.&#xD;&#xA;III - Until end of turn, you may cast instant and sorcery spells from any graveyard. If a spell cast this way would be put into a graveyard, exile it instead. Exile The Great Work, then return it to the battlefield (front face up)."/><property name="Flavor" value=""/><property name="Power" value=""/><property name="Toughness" value=""/><property name="PT Box" value=""/><property name="Artist" value="José Parodi"/><property name="MultiverseId" value="SF-MOM_341b"/><property name="Number" value="341"/></card><card id="6198aeda-6047-4c15-bada-4a62398710b9" name="Vorinclex"><property name="Cost" value="{3}{G}{G}"/><property name="Converted Mana Cost" value="5"/><property name="Color" value="Green"/><property name="Type" value="Legendary Creature"/><property name="Subtype" value="Phyrexian Praetor"/><property name="Rarity" value="Mythic Rare"/><property name="Rules" value="Trample, reach&#xD;&#xA;When Vorinclex enters the battlefield, search your library for up to two Forest cards, reveal them, put them into your hand, then shuffle.&#xD;&#xA;{6}{G}{G}: Exile Vorinclex, then return it to the battlefield transformed under its owner's control. Activate only as a sorcery."/><property name="Flavor" value=""/><property name="Power" value="6"/><property name="Toughness" value="6"/><property name="PT Box" value="6 / 6"/><property name="Artist" value="Joseph Weston"/><property name="MultiverseId" value="SF-MOM_342a"/><property name="Number" value="342"/></card><card id="945e58f4-044e-441f-b11f-8105dfb40163" name="The Grand Evolution"><property name="Cost" value=""/><property name="Converted Mana Cost" value="5"/><property name="Color" value="Green"/><property name="Type" value="Enchantment"/><property name="Subtype" value="Saga"/><property name="Rarity" value="Mythic Rare"/><property name="Rules" value="(As this Saga enters and after your draw step, add a lore counter.)&#xD;&#xA;I - Mill ten cards. Put up to two creature cards from among the milled cards onto the battlefield.&#xD;&#xA;II - Distribute seven +1/+1 counters among any number of target creatures you control.&#xD;&#xA;III - Until end of turn, creatures you control gain &quot;{1}: This creature fights target creature you don't control.&quot; Exile The Grand Evolution, then return it to the battlefield (front face up)."/><property name="Flavor" value=""/><property name="Power" value=""/><property name="Toughness" value=""/><property name="PT Box" value=""/><property name="Artist" value="Joseph Weston"/><property name="MultiverseId" value="SF-MOM_342b"/><property name="Number" value="342"/></card></cards></set>