<?xml version="1.0" encoding="utf-8" standalone="yes"?><set name="Innistrad: Crimson Vow Collector Boosters" id="F0187275-F624-4977-9D4F-74BAD344D19B" gameId="A6C8D2E8-7CD8-11DD-8F94-E62B56D89593" gameVersion="2.0.4" version="3.1"><packaging></packaging><cards><card id="a738eafd-ca90-45b5-a867-cfb6496ed4de" name="A-Binding Geist"><property name="Cost" value="{1}{U}"/><property name="Converted Mana Cost" value="0"/><property name="Color" value="Blue"/><property name="Type" value="Creature"/><property name="Subtype" value="Spirit"/><property name="Rarity" value="Common"/><property name="Rules" value="Whenever Binding Geist attacks, target creature an opponent controls gets -2/-0 until your next turn.&#xD;&#xA;Disturb {U} (You may cast this card from your graveyard transformed for its disturb cost.)"/><property name="Flavor" value=""/><property name="Power" value="2"/><property name="Toughness" value="1"/><property name="PT Box" value="2 / 1"/><property name="Artist" value="Campbell White"/><property name="MultiverseId" value="SF-VOW_A-48a"/><property name="Number" value="A-48"/></card><card id="df36971c-d75b-4aa4-90e4-b47070948d06" name="A-Spectral Binding"><property name="Cost" value=""/><property name="Converted Mana Cost" value="0"/><property name="Color" value="Multicolor White Blue"/><property name="Type" value="Enchantment"/><property name="Subtype" value="Aura"/><property name="Rarity" value="Common"/><property name="Rules" value="Enchant creature&#xD;&#xA;Enchanted creature gets -2/-0.&#xD;&#xA;If Spectral Binding would be put into a graveyard from anywhere, exile it instead."/><property name="Flavor" value=""/><property name="Power" value=""/><property name="Toughness" value=""/><property name="PT Box" value=""/><property name="Artist" value="Campbell White"/><property name="MultiverseId" value="SF-VOW_A-48b"/><property name="Number" value="A-48"/></card><card id="08a0c44d-9611-4c6e-876d-7cc047d958fa" name="A-Cobbled Lancer"><property name="Cost" value="{U}"/><property name="Converted Mana Cost" value="1"/><property name="Color" value="Blue"/><property name="Type" value="Creature"/><property name="Subtype" value="Zombie Horse"/><property name="Rarity" value="Uncommon"/><property name="Rules" value="As an additional cost to cast this spell, exile a creature card from your graveyard.&#xD;&#xA;{1}{U}, Exile Cobbled Lancer from your graveyard: Draw a card."/><property name="Flavor" value="&quot;Don't worry everyone - I hear hoofbeats! The Gavony Riders are coming to save us!&quot;&#xD;&#xA; - Adin, Moorland villager"/><property name="Power" value="3"/><property name="Toughness" value="3"/><property name="PT Box" value="3 / 3"/><property name="Artist" value="Igor Kieryluk"/><property name="MultiverseId" value="SF-VOW_A-52"/><property name="Number" value="A-52"/></card><card id="d541aafe-72c2-4310-83f7-ffd399913cef" name="A-Dreamshackle Geist"><property name="Cost" value="{1}{U}{U}"/><property name="Converted Mana Cost" value="3"/><property name="Color" value="Blue"/><property name="Type" value="Creature"/><property name="Subtype" value="Spirit"/><property name="Rarity" value="Rare"/><property name="Rules" value="Flying&#xD;&#xA;At the beginning of combat on your turn, choose up to one  - &#xD;&#xA;• Tap target creature.&#xD;&#xA;• Target creature doesn't untap during its controller's next untap step."/><property name="Flavor" value=""/><property name="Power" value="3"/><property name="Toughness" value="2"/><property name="PT Box" value="3 / 2"/><property name="Artist" value="Andreas Zafiratos"/><property name="MultiverseId" value="SF-VOW_A-58"/><property name="Number" value="A-58"/></card><card id="5e1415e4-4ae5-4cf4-be1a-ceed69937dfc" name="A-Gutter Skulker"><property name="Cost" value="{2}{U}"/><property name="Converted Mana Cost" value="0"/><property name="Color" value="Blue"/><property name="Type" value="Creature"/><property name="Subtype" value="Spirit"/><property name="Rarity" value="Uncommon"/><property name="Rules" value="Gutter Skulker can't be blocked as long as it's attacking alone.&#xD;&#xA;Disturb {2}{U} (You may cast this card from your graveyard transformed for its disturb cost.)"/><property name="Flavor" value=""/><property name="Power" value="3"/><property name="Toughness" value="3"/><property name="PT Box" value="3 / 3"/><property name="Artist" value="Viko Menezes"/><property name="MultiverseId" value="SF-VOW_A-62a"/><property name="Number" value="A-62"/></card><card id="227bc4a2-d590-4151-98d0-bd24a10741b2" name="A-Gutter Shortcut"><property name="Cost" value=""/><property name="Converted Mana Cost" value="0"/><property name="Color" value="Blue"/><property name="Type" value="Enchantment"/><property name="Subtype" value="Aura"/><property name="Rarity" value="Uncommon"/><property name="Rules" value="Enchant creature&#xD;&#xA;Enchanted creature gets +3/+0. It can't be blocked as long as it's attacking alone.&#xD;&#xA;If Gutter Shortcut would be put into a graveyard from anywhere, exile it instead."/><property name="Flavor" value=""/><property name="Power" value=""/><property name="Toughness" value=""/><property name="PT Box" value=""/><property name="Artist" value="Viko Menezes"/><property name="MultiverseId" value="SF-VOW_A-62b"/><property name="Number" value="A-62"/></card><card id="2a1926cd-b3fb-4352-b80a-2f41c76356c5" name="A-Lantern Bearer"><property name="Cost" value="{U}"/><property name="Converted Mana Cost" value="0"/><property name="Color" value="Blue"/><property name="Type" value="Creature"/><property name="Subtype" value="Spirit"/><property name="Rarity" value="Common"/><property name="Rules" value="Flying&#xD;&#xA;Disturb {1}{U} (You may cast this card from your graveyard transformed for its disturb cost.)"/><property name="Flavor" value=""/><property name="Power" value="1"/><property name="Toughness" value="1"/><property name="PT Box" value="1 / 1"/><property name="Artist" value="Zoltan Boros"/><property name="MultiverseId" value="SF-VOW_A-66a"/><property name="Number" value="A-66"/></card><card id="65adc734-47bf-41c4-a32a-bd032d749f07" name="A-Lanterns' Lift"><property name="Cost" value=""/><property name="Converted Mana Cost" value="0"/><property name="Color" value="Multicolor Blue Black"/><property name="Type" value="Enchantment"/><property name="Subtype" value="Aura"/><property name="Rarity" value="Common"/><property name="Rules" value="Enchant creature&#xD;&#xA;Enchanted creature gets +1/+1 and has flying.&#xD;&#xA;If Lanterns' Lift would be put into a graveyard from anywhere, exile it instead."/><property name="Flavor" value=""/><property name="Power" value=""/><property name="Toughness" value=""/><property name="PT Box" value=""/><property name="Artist" value="Zoltan Boros"/><property name="MultiverseId" value="SF-VOW_A-66b"/><property name="Number" value="A-66"/></card><card id="06097d08-9864-44eb-9a3c-54d231f59bc3" name="A-Mischievous Catgeist"><property name="Cost" value="{1}{U}"/><property name="Converted Mana Cost" value="0"/><property name="Color" value="Blue"/><property name="Type" value="Creature"/><property name="Subtype" value="Cat Spirit"/><property name="Rarity" value="Uncommon"/><property name="Rules" value="Whenever Mischievous Catgeist deals combat damage to a player, draw a card.&#xD;&#xA;Disturb {1}{U} (You may cast this card from your graveyard transformed for its disturb cost.)"/><property name="Flavor" value=""/><property name="Power" value="1"/><property name="Toughness" value="1"/><property name="PT Box" value="1 / 1"/><property name="Artist" value="Denman Rooke"/><property name="MultiverseId" value="SF-VOW_A-69a"/><property name="Number" value="A-69"/></card><card id="db22086a-6ace-4b88-a4e1-6c960a66c272" name="A-Catlike Curiosity"><property name="Cost" value=""/><property name="Converted Mana Cost" value="0"/><property name="Color" value="Multicolor Blue Red"/><property name="Type" value="Enchantment"/><property name="Subtype" value="Aura"/><property name="Rarity" value="Uncommon"/><property name="Rules" value="Enchant creature&#xD;&#xA;Enchanted creature gets +1/+1.&#xD;&#xA;Enchanted creature has &quot;Whenever this creature deals combat damage to a player, draw a card.&quot;&#xD;&#xA;If Catlike Curiosity would be put into a graveyard from anywhere, exile it instead."/><property name="Flavor" value=""/><property name="Power" value=""/><property name="Toughness" value=""/><property name="PT Box" value=""/><property name="Artist" value="Denman Rooke"/><property name="MultiverseId" value="SF-VOW_A-69b"/><property name="Number" value="A-69"/></card><card id="fd67ce4f-ce9e-4ba7-a7b1-f1d73e29df1e" name="A-Stitched Assistant"><property name="Cost" value="{1}{U}"/><property name="Converted Mana Cost" value="2"/><property name="Color" value="Blue"/><property name="Type" value="Creature"/><property name="Subtype" value="Zombie"/><property name="Rarity" value="Common"/><property name="Rules" value="Exploit&#xD;&#xA;When Stitched Assistant exploits a creature, scry 2, then draw a card."/><property name="Flavor" value=""/><property name="Power" value="2"/><property name="Toughness" value="1"/><property name="PT Box" value="2 / 1"/><property name="Artist" value="Andrey Kuzinskiy"/><property name="MultiverseId" value="SF-VOW_A-81"/><property name="Number" value="A-81"/></card><card id="d779a2b7-7161-4490-9b5f-f6ef98d60c8d" name="A-Brine Comber"><property name="Cost" value="{1}{W}{U}"/><property name="Converted Mana Cost" value="0"/><property name="Color" value="Multicolor White Blue"/><property name="Type" value="Creature"/><property name="Subtype" value="Spirit"/><property name="Rarity" value="Uncommon"/><property name="Rules" value="Whenever Brine Comber enters the battlefield or becomes the target of an Aura spell, create a 1/1 white Spirit creature token with flying.&#xD;&#xA;Disturb {W}{U} (You may cast this card from your graveyard transformed for its disturb cost.)"/><property name="Flavor" value=""/><property name="Power" value="2"/><property name="Toughness" value="2"/><property name="PT Box" value="2 / 2"/><property name="Artist" value="Olena Richards"/><property name="MultiverseId" value="SF-VOW_A-233a"/><property name="Number" value="A-233"/></card><card id="0aaf6568-2bf0-4d6c-9338-803f06def37e" name="A-Brinebound Gift"><property name="Cost" value=""/><property name="Converted Mana Cost" value="0"/><property name="Color" value="Multicolor White Blue"/><property name="Type" value="Enchantment"/><property name="Subtype" value="Aura"/><property name="Rarity" value="Uncommon"/><property name="Rules" value="Enchant creature&#xD;&#xA;Whenever Brinebound Gift enters the battlefield or enchanted creature becomes the target of an Aura spell, create a 1/1 white Spirit creature token with flying.&#xD;&#xA;If Brinebound Gift would be put into a graveyard from anywhere, exile it instead."/><property name="Flavor" value=""/><property name="Power" value=""/><property name="Toughness" value=""/><property name="PT Box" value=""/><property name="Artist" value="Olena Richards"/><property name="MultiverseId" value="SF-VOW_A-233b"/><property name="Number" value="A-233"/></card><card id="4ebbdee6-ead4-4ccc-a64f-e503d67552b3" name="A-Dorothea, Vengeful Victim"><property name="Cost" value="{W}{U}"/><property name="Converted Mana Cost" value="0"/><property name="Color" value="Multicolor White Blue"/><property name="Type" value="Legendary Creature"/><property name="Subtype" value="Spirit"/><property name="Rarity" value="Rare"/><property name="Rules" value="Flying&#xD;&#xA;When Dorothea, Vengeful Victim attacks or blocks, sacrifice it at end of combat.&#xD;&#xA;Disturb {W}{U} (You may cast this card from your graveyard transformed for its disturb cost.)"/><property name="Flavor" value=""/><property name="Power" value="4"/><property name="Toughness" value="4"/><property name="PT Box" value="4 / 4"/><property name="Artist" value="Marta Nael"/><property name="MultiverseId" value="SF-VOW_A-235a"/><property name="Number" value="A-235"/></card><card id="64de13f2-db4d-45bf-a75d-7eb7881b38b5" name="A-Dorothea's Retribution"><property name="Cost" value=""/><property name="Converted Mana Cost" value="0"/><property name="Color" value="Multicolor White Blue"/><property name="Type" value="Enchantment"/><property name="Subtype" value="Aura"/><property name="Rarity" value="Rare"/><property name="Rules" value="Enchant creature&#xD;&#xA;Enchanted creature has &quot;Whenever this creature attacks, create a 4/4 white Spirit creature token with flying that's tapped and attacking. Sacrifice that token at end of combat.&quot;&#xD;&#xA;If Dorothea's Retribution would be put into a graveyard from anywhere, exile it instead."/><property name="Flavor" value=""/><property name="Power" value=""/><property name="Toughness" value=""/><property name="PT Box" value=""/><property name="Artist" value="Marta Nael"/><property name="MultiverseId" value="SF-VOW_A-235b"/><property name="Number" value="A-235"/></card><card id="2eab2160-0aa4-4450-8bf4-c87abaa37818" name="A-Sigardian Paladin"><property name="Cost" value="{1}{G}{W}"/><property name="Converted Mana Cost" value="3"/><property name="Color" value="Multicolor White Green"/><property name="Type" value="Creature"/><property name="Subtype" value="Human Knight"/><property name="Rarity" value="Uncommon"/><property name="Rules" value="As long as you've put one or more +1/+1 counters on a creature this turn, Sigardian Paladin has trample and lifelink.&#xD;&#xA;{G}{W}: Target creature you control with a +1/+1 counter on it gains trample and lifelink until end of turn."/><property name="Flavor" value=""/><property name="Power" value="4"/><property name="Toughness" value="3"/><property name="PT Box" value="4 / 3"/><property name="Artist" value="Slawomir Maniak"/><property name="MultiverseId" value="SF-VOW_A-247"/><property name="Number" value="A-247"/></card><card id="4c62f861-41e8-49c5-9796-230a2c58ade0" name="A-Skull Skaab"><property name="Cost" value="{U}{B}"/><property name="Converted Mana Cost" value="2"/><property name="Color" value="Multicolor Blue Black"/><property name="Type" value="Creature"/><property name="Subtype" value="Zombie"/><property name="Rarity" value="Uncommon"/><property name="Rules" value="Exploit (When this creature enters the battlefield, you may sacrifice a creature.)&#xD;&#xA;Whenever a creature you control exploits a creature, create a 2/2 black Zombie creature token."/><property name="Flavor" value=""/><property name="Power" value="2"/><property name="Toughness" value="2"/><property name="PT Box" value="2 / 2"/><property name="Artist" value="Nicholas Gregory"/><property name="MultiverseId" value="SF-VOW_A-248"/><property name="Number" value="A-248"/></card><card id="0e0105f0-4b92-49b8-8f67-35f47a4b0a05" name="Bloodsworn Squire"><property name="Cost" value="{3}{B}"/><property name="Converted Mana Cost" value="4"/><property name="Color" value="Black"/><property name="Type" value="Creature"/><property name="Subtype" value="Vampire Soldier"/><property name="Rarity" value="Uncommon"/><property name="Rules" value="{1}{B}, Discard a card: Bloodsworn Squire gains indestructible until end of turn. Tap it. Then if there are four or more creature cards in your graveyard, transform Bloodsworn Squire. (Damage and effects that say &quot;destroy&quot; don't destroy it.)"/><property name="Flavor" value=""/><property name="Power" value="3"/><property name="Toughness" value="3"/><property name="PT Box" value="3 / 3"/><property name="Artist" value="Karl Kopinski"/><property name="MultiverseId" value="SF-VOW_289a"/><property name="Number" value="289"/></card><card id="87757b73-2186-4892-b892-a6ec8dd4d3fd" name="Bloodsworn Knight"><property name="Cost" value=""/><property name="Converted Mana Cost" value="4"/><property name="Color" value="Black"/><property name="Type" value="Creature"/><property name="Subtype" value="Vampire Knight"/><property name="Rarity" value="Uncommon"/><property name="Rules" value="Bloodsworn Knight's power and toughness are each equal to the number of creature cards in your graveyard.&#xD;&#xA;{1}{B}, Discard a card: Bloodsworn Knight gains indestructible until end of turn. Tap it. (Damage and effects that say &quot;destroy&quot; don't destroy it.)"/><property name="Flavor" value=""/><property name="Power" value="*"/><property name="Toughness" value="*"/><property name="PT Box" value="* / *"/><property name="Artist" value="Karl Kopinski"/><property name="MultiverseId" value="SF-VOW_289b"/><property name="Number" value="289"/></card><card id="ae982366-168b-4b66-a92c-4b889df1a396" name="Henrika Domnathi"><property name="Cost" value="{2}{B}{B}"/><property name="Converted Mana Cost" value="4"/><property name="Color" value="Black"/><property name="Type" value="Legendary Creature"/><property name="Subtype" value="Vampire"/><property name="Rarity" value="Mythic Rare"/><property name="Rules" value="Flying&#xD;&#xA;At the beginning of combat on your turn, choose one that hasn't been chosen  - &#xD;&#xA;• Each player sacrifices a creature.&#xD;&#xA;• You draw a card and you lose 1 life.&#xD;&#xA;• Transform Henrika Domnathi."/><property name="Flavor" value=""/><property name="Power" value="1"/><property name="Toughness" value="3"/><property name="PT Box" value="1 / 3"/><property name="Artist" value="Jason A. Engle"/><property name="MultiverseId" value="SF-VOW_293a"/><property name="Number" value="293"/></card><card id="0bf5fe1d-b8d1-4a75-8c0c-27fbf261da24" name="Henrika, Infernal Seer"><property name="Cost" value=""/><property name="Converted Mana Cost" value="4"/><property name="Color" value="Black"/><property name="Type" value="Legendary Creature"/><property name="Subtype" value="Vampire"/><property name="Rarity" value="Mythic Rare"/><property name="Rules" value="Flying, deathtouch, lifelink&#xD;&#xA;{1}{B}{B}: Each creature you control with flying, deathtouch, and/or lifelink gets +1/+0 until end of turn."/><property name="Flavor" value=""/><property name="Power" value="3"/><property name="Toughness" value="4"/><property name="PT Box" value="3 / 4"/><property name="Artist" value="Jason A. Engle"/><property name="MultiverseId" value="SF-VOW_293b"/><property name="Number" value="293"/></card><card id="ab1350df-c4c2-4364-a56f-d0aa22abc2e7" name="Innocent Traveler"><property name="Cost" value="{2}{B}{B}"/><property name="Converted Mana Cost" value="4"/><property name="Color" value="Black"/><property name="Type" value="Creature"/><property name="Subtype" value="Human"/><property name="Rarity" value="Uncommon"/><property name="Rules" value="At the beginning of your upkeep, any opponent may sacrifice a creature. If no one does, transform Innocent Traveler."/><property name="Flavor" value=""/><property name="Power" value="1"/><property name="Toughness" value="3"/><property name="PT Box" value="1 / 3"/><property name="Artist" value="Sami Makkonen"/><property name="MultiverseId" value="SF-VOW_294a"/><property name="Number" value="294"/></card><card id="2981bbf8-1cbc-48b0-a3ff-9ae68288298a" name="Malicious Invader"><property name="Cost" value=""/><property name="Converted Mana Cost" value="4"/><property name="Color" value="Black"/><property name="Type" value="Creature"/><property name="Subtype" value="Vampire"/><property name="Rarity" value="Uncommon"/><property name="Rules" value="Flying&#xD;&#xA;Malicious Invader gets +2/+0 as long as an opponent controls a Human."/><property name="Flavor" value=""/><property name="Power" value="3"/><property name="Toughness" value="3"/><property name="PT Box" value="3 / 3"/><property name="Artist" value="Sami Makkonen"/><property name="MultiverseId" value="SF-VOW_294b"/><property name="Number" value="294"/></card><card id="ab8c0869-820c-4ea4-b3cf-91071c12c749" name="Restless Bloodseeker"><property name="Cost" value="{1}{B}"/><property name="Converted Mana Cost" value="2"/><property name="Color" value="Black"/><property name="Type" value="Creature"/><property name="Subtype" value="Vampire"/><property name="Rarity" value="Uncommon"/><property name="Rules" value="At the beginning of your end step, if you gained life this turn, create a Blood token. (It's an artifact with &quot;{1}, {T}, Discard a card, Sacrifice this artifact: Draw a card.&quot;)&#xD;&#xA;Sacrifice two Blood tokens: Transform Restless Bloodseeker. Activate only as a sorcery."/><property name="Flavor" value=""/><property name="Power" value="1"/><property name="Toughness" value="3"/><property name="PT Box" value="1 / 3"/><property name="Artist" value="Christian Angel"/><property name="MultiverseId" value="SF-VOW_295a"/><property name="Number" value="295"/></card><card id="43a633a7-dcbd-49bb-8d3f-7bb137fff4e3" name="Bloodsoaked Reveler"><property name="Cost" value=""/><property name="Converted Mana Cost" value="2"/><property name="Color" value="Black"/><property name="Type" value="Creature"/><property name="Subtype" value="Vampire"/><property name="Rarity" value="Uncommon"/><property name="Rules" value="At the beginning of your end step, if you gained life this turn, create a Blood token. (It's an artifact with &quot;{1}, {T}, Discard a card, Sacrifice this artifact: Draw a card.&quot;)&#xD;&#xA;{4}{B}: Each opponent loses 2 life and you gain 2 life."/><property name="Flavor" value=""/><property name="Power" value="3"/><property name="Toughness" value="3"/><property name="PT Box" value="3 / 3"/><property name="Artist" value="Christian Angel"/><property name="MultiverseId" value="SF-VOW_295b"/><property name="Number" value="295"/></card><card id="105ac1bb-dd11-44cb-8e84-7db2486ed266" name="Voldaren Bloodcaster"><property name="Cost" value="{1}{B}"/><property name="Converted Mana Cost" value="2"/><property name="Color" value="Black"/><property name="Type" value="Creature"/><property name="Subtype" value="Vampire Wizard"/><property name="Rarity" value="Rare"/><property name="Rules" value="Flying&#xD;&#xA;Whenever Voldaren Bloodcaster or another nontoken creature you control dies, create a Blood token. (It's an artifact with &quot;{1}, {T}, Discard a card, Sacrifice this artifact: Draw a card.&quot;)&#xD;&#xA;Whenever you create a Blood token, if you control five or more Blood tokens, transform Voldaren Bloodcaster."/><property name="Flavor" value=""/><property name="Power" value="2"/><property name="Toughness" value="1"/><property name="PT Box" value="2 / 1"/><property name="Artist" value="Samuel Araya"/><property name="MultiverseId" value="SF-VOW_298a"/><property name="Number" value="298"/></card><card id="c0f8321b-df70-4797-a429-6450d0fa1a32" name="Bloodbat Summoner"><property name="Cost" value=""/><property name="Converted Mana Cost" value="2"/><property name="Color" value="Black"/><property name="Type" value="Creature"/><property name="Subtype" value="Vampire Wizard"/><property name="Rarity" value="Rare"/><property name="Rules" value="Flying&#xD;&#xA;At the beginning of combat on your turn, up to one target Blood token you control becomes a 2/2 black Bat creature with flying and haste in addition to its other types."/><property name="Flavor" value=""/><property name="Power" value="3"/><property name="Toughness" value="3"/><property name="PT Box" value="3 / 3"/><property name="Artist" value="Samuel Araya"/><property name="MultiverseId" value="SF-VOW_298b"/><property name="Number" value="298"/></card><card id="e0208783-45b8-4aa2-a3f6-cd72bb586e00" name="Alluring Suitor"><property name="Cost" value="{2}{R}"/><property name="Converted Mana Cost" value="3"/><property name="Color" value="Red"/><property name="Type" value="Creature"/><property name="Subtype" value="Vampire"/><property name="Rarity" value="Uncommon"/><property name="Rules" value="When you attack with exactly two creatures, transform Alluring Suitor."/><property name="Flavor" value=""/><property name="Power" value="2"/><property name="Toughness" value="3"/><property name="PT Box" value="2 / 3"/><property name="Artist" value="Zinna Du"/><property name="MultiverseId" value="SF-VOW_300a"/><property name="Number" value="300"/></card><card id="96d14383-5eff-4655-a350-ff53aafbcf4b" name="Deadly Dancer"><property name="Cost" value=""/><property name="Converted Mana Cost" value="3"/><property name="Color" value="Red"/><property name="Type" value="Creature"/><property name="Subtype" value="Vampire"/><property name="Rarity" value="Uncommon"/><property name="Rules" value="Trample&#xD;&#xA;When this creature transforms into Deadly Dancer, add {R}{R}. Until end of turn, you don't lose this mana as steps and phases end.&#xD;&#xA;{R}{R}: Deadly Dancer and another target creature each get +1/+0 until end of turn."/><property name="Flavor" value=""/><property name="Power" value="3"/><property name="Toughness" value="3"/><property name="PT Box" value="3 / 3"/><property name="Artist" value="Zinna Du"/><property name="MultiverseId" value="SF-VOW_300b"/><property name="Number" value="300"/></card><card id="af603e61-b840-4ac2-9a8d-e0d1bb45232a" name="Edgar, Charmed Groom"><property name="Cost" value="{2}{W}{B}"/><property name="Converted Mana Cost" value="4"/><property name="Color" value="Multicolor White Black"/><property name="Type" value="Legendary Creature"/><property name="Subtype" value="Vampire Noble"/><property name="Rarity" value="Rare"/><property name="Rules" value="Other Vampires you control get +1/+1.&#xD;&#xA;When Edgar, Charmed Groom dies, return it to the battlefield transformed under its owner's control."/><property name="Flavor" value=""/><property name="Power" value="4"/><property name="Toughness" value="4"/><property name="PT Box" value="4 / 4"/><property name="Artist" value="Néstor Ossandón Leal"/><property name="MultiverseId" value="SF-VOW_311a"/><property name="Number" value="311"/></card><card id="edaabe24-d718-4be2-be6b-42fe2a3e74dc" name="Edgar Markov's Coffin"><property name="Cost" value=""/><property name="Converted Mana Cost" value="4"/><property name="Color" value="Multicolor White Black"/><property name="Type" value="Legendary Artifact"/><property name="Subtype" value=""/><property name="Rarity" value="Rare"/><property name="Rules" value="At the beginning of your upkeep, create a 1/1 white and black Vampire creature token with lifelink and put a bloodline counter on Edgar Markov's Coffin. Then if there are three or more bloodline counters on it, remove those counters and transform it."/><property name="Flavor" value=""/><property name="Power" value=""/><property name="Toughness" value=""/><property name="PT Box" value=""/><property name="Artist" value="Néstor Ossandón Leal"/><property name="MultiverseId" value="SF-VOW_311b"/><property name="Number" value="311"/></card><card id="c939c82f-1b7b-4e73-a8df-be8500f6f19a" name="Runo Stromkirk"><property name="Cost" value="{1}{U}{B}"/><property name="Converted Mana Cost" value="3"/><property name="Color" value="Multicolor Blue Black"/><property name="Type" value="Legendary Creature"/><property name="Subtype" value="Vampire Cleric"/><property name="Rarity" value="Rare"/><property name="Rules" value="Flying&#xD;&#xA;When Runo Stromkirk enters the battlefield, put up to one target creature card from your graveyard on top of your library.&#xD;&#xA;At the beginning of your upkeep, look at the top card of your library. You may reveal that card. If a creature card with mana value 6 or greater is revealed this way, transform Runo Stromkirk."/><property name="Flavor" value=""/><property name="Power" value="1"/><property name="Toughness" value="4"/><property name="PT Box" value="1 / 4"/><property name="Artist" value="Xiaobotong"/><property name="MultiverseId" value="SF-VOW_316a"/><property name="Number" value="316"/></card><card id="9bd0de06-4b64-49d6-adc2-7ef813eb0eaa" name="Krothuss, Lord of the Deep"><property name="Cost" value=""/><property name="Converted Mana Cost" value="3"/><property name="Color" value="Multicolor Blue Black"/><property name="Type" value="Legendary Creature"/><property name="Subtype" value="Kraken Horror"/><property name="Rarity" value="Rare"/><property name="Rules" value="Flying&#xD;&#xA;Whenever Krothuss, Lord of the Deep attacks, create a tapped and attacking token that's a copy of another target attacking creature. If that creature is a Kraken, Leviathan, Octopus, or Serpent, create two of those tokens instead."/><property name="Flavor" value=""/><property name="Power" value="3"/><property name="Toughness" value="5"/><property name="PT Box" value="3 / 5"/><property name="Artist" value="Xiaobotong"/><property name="MultiverseId" value="SF-VOW_316b"/><property name="Number" value="316"/></card><card id="29d7a383-5308-4375-9448-34e74990c219" name="Katilda, Dawnhart Martyr"><property name="Cost" value="{1}{W}{W}"/><property name="Converted Mana Cost" value="3"/><property name="Color" value="White"/><property name="Type" value="Legendary Creature"/><property name="Subtype" value="Spirit Warlock"/><property name="Rarity" value="Rare"/><property name="Rules" value="Flying, lifelink, protection from Vampires&#xD;&#xA;Katilda, Dawnhart Martyr's power and toughness are each equal to the number of permanents you control that are Spirits and/or enchantments.&#xD;&#xA;Disturb {3}{W}{W} (You may cast this card from your graveyard transformed for its disturb cost.)"/><property name="Flavor" value=""/><property name="Power" value="*"/><property name="Toughness" value="*"/><property name="PT Box" value="* / *"/><property name="Artist" value="Joao Ruas"/><property name="MultiverseId" value="SF-VOW_317a"/><property name="Number" value="317"/></card><card id="579011f2-9d5b-4fd0-88ed-331fc714d8d0" name="Katilda's Rising Dawn"><property name="Cost" value=""/><property name="Converted Mana Cost" value="3"/><property name="Color" value="White"/><property name="Type" value="Legendary Enchantment"/><property name="Subtype" value="Aura"/><property name="Rarity" value="Rare"/><property name="Rules" value="Enchant creature&#xD;&#xA;Enchanted creature has flying, lifelink, and protection from Vampires, and it gets +X/+X, where X is the number of permanents you control that are Spirits and/or enchantments.&#xD;&#xA;If Katilda's Rising Dawn would be put into a graveyard from anywhere, exile it instead."/><property name="Flavor" value=""/><property name="Power" value=""/><property name="Toughness" value=""/><property name="PT Box" value=""/><property name="Artist" value="Joao Ruas"/><property name="MultiverseId" value="SF-VOW_317b"/><property name="Number" value="317"/></card><card id="85165cb9-d1bc-47e3-a92b-268d7e25f732" name="Jacob Hauken, Inspector"><property name="Cost" value="{1}{U}"/><property name="Converted Mana Cost" value="2"/><property name="Color" value="Blue"/><property name="Type" value="Legendary Creature"/><property name="Subtype" value="Human Advisor"/><property name="Rarity" value="Mythic Rare"/><property name="Rules" value="{T}: Draw a card, then exile a card from your hand face down. You may look at that card for as long as it remains exiled. You may pay {4}{U}{U}. If you do, transform Jacob Hauken, Inspector."/><property name="Flavor" value=""/><property name="Power" value="0"/><property name="Toughness" value="2"/><property name="PT Box" value="0 / 2"/><property name="Artist" value="Milivoj Ćeran"/><property name="MultiverseId" value="SF-VOW_320a"/><property name="Number" value="320"/></card><card id="a4bef4e6-02c1-4c3f-b8c1-daec19ab06cc" name="Hauken's Insight"><property name="Cost" value=""/><property name="Converted Mana Cost" value="2"/><property name="Color" value="Blue"/><property name="Type" value="Legendary Enchantment"/><property name="Subtype" value=""/><property name="Rarity" value="Mythic Rare"/><property name="Rules" value="At the beginning of your upkeep, exile the top card of your library face down. You may look at that card for as long as it remains exiled.&#xD;&#xA;Once during each of your turns, you may play a land or cast a spell from among the cards exiled with this permanent without paying its mana cost."/><property name="Flavor" value=""/><property name="Power" value=""/><property name="Toughness" value=""/><property name="PT Box" value=""/><property name="Artist" value="Milivoj Ćeran"/><property name="MultiverseId" value="SF-VOW_320b"/><property name="Number" value="320"/></card><card id="09a00e8b-f0d7-4c27-97e0-0d3d6c8db6be" name="Dorothea, Vengeful Victim"><property name="Cost" value="{W}{U}"/><property name="Converted Mana Cost" value="2"/><property name="Color" value="Multicolor White Blue"/><property name="Type" value="Legendary Creature"/><property name="Subtype" value="Spirit"/><property name="Rarity" value="Rare"/><property name="Rules" value="Flying&#xD;&#xA;When Dorothea, Vengeful Victim attacks or blocks, sacrifice it at end of combat.&#xD;&#xA;Disturb {1}{W}{U} (You may cast this card from your graveyard transformed for its disturb cost.)"/><property name="Flavor" value=""/><property name="Power" value="4"/><property name="Toughness" value="4"/><property name="PT Box" value="4 / 4"/><property name="Artist" value="Karmazid"/><property name="MultiverseId" value="SF-VOW_322a"/><property name="Number" value="322"/></card><card id="a6441975-c08e-43cf-a943-067b042e0f33" name="Dorothea's Retribution"><property name="Cost" value=""/><property name="Converted Mana Cost" value="2"/><property name="Color" value="Multicolor White Blue"/><property name="Type" value="Enchantment"/><property name="Subtype" value="Aura"/><property name="Rarity" value="Rare"/><property name="Rules" value="Enchant creature&#xD;&#xA;Enchanted creature has &quot;Whenever this creature attacks, create a 4/4 white Spirit creature token with flying that's tapped and attacking. Sacrifice that token at end of combat.&quot;&#xD;&#xA;If Dorothea's Retribution would be put into a graveyard from anywhere, exile it instead."/><property name="Flavor" value=""/><property name="Power" value=""/><property name="Toughness" value=""/><property name="PT Box" value=""/><property name="Artist" value="Karmazid"/><property name="MultiverseId" value="SF-VOW_322b"/><property name="Number" value="322"/></card><card id="4b855c36-e6b6-4802-8f8c-eeda504e336f" name="Runo Stromkirk"><property name="Cost" value="{1}{U}{B}"/><property name="Converted Mana Cost" value="3"/><property name="Color" value="Multicolor Blue Black"/><property name="Type" value="Legendary Creature"/><property name="Subtype" value="Vampire Cleric"/><property name="Rarity" value="Rare"/><property name="Rules" value="Flying&#xD;&#xA;When Runo Stromkirk enters the battlefield, put up to one target creature card from your graveyard on top of your library.&#xD;&#xA;At the beginning of your upkeep, look at the top card of your library. You may reveal that card. If a creature card with mana value 6 or greater is revealed this way, transform Runo Stromkirk."/><property name="Flavor" value=""/><property name="Power" value="1"/><property name="Toughness" value="4"/><property name="PT Box" value="1 / 4"/><property name="Artist" value="Nico Delort"/><property name="MultiverseId" value="SF-VOW_327a"/><property name="Number" value="327"/></card><card id="1ea9922d-c9f6-4973-8e4a-82f9b4b0106b" name="Krothuss, Lord of the Deep"><property name="Cost" value=""/><property name="Converted Mana Cost" value="3"/><property name="Color" value="Multicolor Blue Black"/><property name="Type" value="Legendary Creature"/><property name="Subtype" value="Kraken Horror"/><property name="Rarity" value="Rare"/><property name="Rules" value="Flying&#xD;&#xA;Whenever Krothuss, Lord of the Deep attacks, create a tapped and attacking token that's a copy of another target attacking creature. If that creature is a Kraken, Leviathan, Octopus, or Serpent, create two of those tokens instead."/><property name="Flavor" value=""/><property name="Power" value="3"/><property name="Toughness" value="5"/><property name="PT Box" value="3 / 5"/><property name="Artist" value="Nico Delort"/><property name="MultiverseId" value="SF-VOW_327b"/><property name="Number" value="327"/></card><card id="fc5f3b4f-80a1-4393-b6d7-9ba82df90bfa" name="Jacob Hauken, Inspector"><property name="Cost" value="{1}{U}"/><property name="Converted Mana Cost" value="2"/><property name="Color" value="Blue"/><property name="Type" value="Legendary Creature"/><property name="Subtype" value="Human Advisor"/><property name="Rarity" value="Mythic Rare"/><property name="Rules" value="{T}: Draw a card, then exile a card from your hand face down. You may look at that card for as long as it remains exiled. You may pay {4}{U}{U}. If you do, transform Jacob Hauken, Inspector."/><property name="Flavor" value=""/><property name="Power" value="0"/><property name="Toughness" value="2"/><property name="PT Box" value="0 / 2"/><property name="Artist" value="Slawomir Maniak"/><property name="MultiverseId" value="SF-VOW_332a"/><property name="Number" value="332"/></card><card id="da414bfe-87fd-4440-ba3a-22e313d816f5" name="Hauken's Insight"><property name="Cost" value=""/><property name="Converted Mana Cost" value="2"/><property name="Color" value="Blue"/><property name="Type" value="Legendary Enchantment"/><property name="Subtype" value=""/><property name="Rarity" value="Mythic Rare"/><property name="Rules" value="At the beginning of your upkeep, exile the top card of your library face down. You may look at that card for as long as it remains exiled.&#xD;&#xA;Once during each of your turns, you may play a land or cast a spell from among the cards exiled with this permanent without paying its mana cost."/><property name="Flavor" value=""/><property name="Power" value=""/><property name="Toughness" value=""/><property name="PT Box" value=""/><property name="Artist" value="Slawomir Maniak"/><property name="MultiverseId" value="SF-VOW_332b"/><property name="Number" value="332"/></card><card id="c0e81a2b-15d6-44ff-bc2a-66a80166adf3" name="Henrika Domnathi"><property name="Cost" value="{2}{B}{B}"/><property name="Converted Mana Cost" value="4"/><property name="Color" value="Black"/><property name="Type" value="Legendary Creature"/><property name="Subtype" value="Vampire"/><property name="Rarity" value="Mythic Rare"/><property name="Rules" value="Flying&#xD;&#xA;At the beginning of combat on your turn, choose one that hasn't been chosen  - &#xD;&#xA;• Each player sacrifices a creature.&#xD;&#xA;• You draw a card and you lose 1 life.&#xD;&#xA;• Transform Henrika Domnathi."/><property name="Flavor" value=""/><property name="Power" value="1"/><property name="Toughness" value="3"/><property name="PT Box" value="1 / 3"/><property name="Artist" value="Nils Hamm"/><property name="MultiverseId" value="SF-VOW_335a"/><property name="Number" value="335"/></card><card id="194d424f-3954-4e24-9584-c6b048159e67" name="Henrika, Infernal Seer"><property name="Cost" value=""/><property name="Converted Mana Cost" value="4"/><property name="Color" value="Black"/><property name="Type" value="Legendary Creature"/><property name="Subtype" value="Vampire"/><property name="Rarity" value="Mythic Rare"/><property name="Rules" value="Flying, deathtouch, lifelink&#xD;&#xA;{1}{B}{B}: Each creature you control with flying, deathtouch, and/or lifelink gets +1/+0 until end of turn."/><property name="Flavor" value="Nothing can be more dreadful than those awful women, who were - who are - waiting to suck my blood."/><property name="Power" value="3"/><property name="Toughness" value="4"/><property name="PT Box" value="3 / 4"/><property name="Artist" value="Nils Hamm"/><property name="MultiverseId" value="SF-VOW_335b"/><property name="Number" value="335"/></card><card id="b35ad3ba-8959-4cec-aa57-433f50d66fb0" name="Innocent Traveler"><property name="Cost" value="{2}{B}{B}"/><property name="Converted Mana Cost" value="4"/><property name="Color" value="Black"/><property name="Type" value="Creature"/><property name="Subtype" value="Human"/><property name="Rarity" value="Uncommon"/><property name="Rules" value="At the beginning of your upkeep, any opponent may sacrifice a creature. If no one does, transform Innocent Traveler."/><property name="Flavor" value="I looked at her throat just now as she lay asleep, and the tiny wounds seem not to have healed."/><property name="Power" value="1"/><property name="Toughness" value="3"/><property name="PT Box" value="1 / 3"/><property name="Artist" value="Igor Kieryluk"/><property name="MultiverseId" value="SF-VOW_336a"/><property name="Number" value="336"/></card><card id="fea9fc7f-63e2-4bac-bf68-5d3ba6fd333b" name="Malicious Invader"><property name="Cost" value=""/><property name="Converted Mana Cost" value="4"/><property name="Color" value="Black"/><property name="Type" value="Creature"/><property name="Subtype" value="Vampire"/><property name="Rarity" value="Uncommon"/><property name="Rules" value="Flying&#xD;&#xA;Malicious Invader gets +2/+0 as long as an opponent controls a Human."/><property name="Flavor" value="Van Helsing raised his lantern and drew the slide; by the concentrated light that fell on Lucy's face we could see that the lips were crimson with fresh blood."/><property name="Power" value="3"/><property name="Toughness" value="3"/><property name="PT Box" value="3 / 3"/><property name="Artist" value="Igor Kieryluk"/><property name="MultiverseId" value="SF-VOW_336b"/><property name="Number" value="336"/></card><card id="61d4b77b-e9b9-4199-b966-a6992a2c604e" name="Voldaren Bloodcaster"><property name="Cost" value="{1}{B}"/><property name="Converted Mana Cost" value="2"/><property name="Color" value="Black"/><property name="Type" value="Creature"/><property name="Subtype" value="Vampire Wizard"/><property name="Rarity" value="Rare"/><property name="Rules" value="Flying&#xD;&#xA;Whenever Voldaren Bloodcaster or another nontoken creature you control dies, create a Blood token. (It's an artifact with &quot;{1}, {T}, Discard a card, Sacrifice this artifact: Draw a card.&quot;)&#xD;&#xA;Whenever you create a Blood token, if you control five or more Blood tokens, transform Voldaren Bloodcaster."/><property name="Flavor" value=""/><property name="Power" value="2"/><property name="Toughness" value="1"/><property name="PT Box" value="2 / 1"/><property name="Artist" value="Johann Bodin"/><property name="MultiverseId" value="SF-VOW_338a"/><property name="Number" value="338"/></card><card id="6c6bdcb6-5d23-4147-ac52-753c86381070" name="Bloodbat Summoner"><property name="Cost" value=""/><property name="Converted Mana Cost" value="2"/><property name="Color" value="Black"/><property name="Type" value="Creature"/><property name="Subtype" value="Vampire Wizard"/><property name="Rarity" value="Rare"/><property name="Rules" value="Flying&#xD;&#xA;At the beginning of combat on your turn, up to one target Blood token you control becomes a 2/2 black Bat creature with flying and haste in addition to its other types."/><property name="Flavor" value="&quot;Do you mean to tell me that Lucy was bitten by such a bat . . . ?&quot;"/><property name="Power" value="3"/><property name="Toughness" value="3"/><property name="PT Box" value="3 / 3"/><property name="Artist" value="Johann Bodin"/><property name="MultiverseId" value="SF-VOW_338b"/><property name="Number" value="338"/></card><card id="cd09e258-4b82-414b-970b-9469eba926ab" name="Edgar, Charmed Groom"><property name="Cost" value="{2}{W}{B}"/><property name="Converted Mana Cost" value="4"/><property name="Color" value="Multicolor White Black"/><property name="Type" value="Legendary Creature"/><property name="Subtype" value="Vampire Noble"/><property name="Rarity" value="Rare"/><property name="Rules" value="Other Vampires you control get +1/+1.&#xD;&#xA;When Edgar, Charmed Groom dies, return it to the battlefield transformed under its owner's control."/><property name="Flavor" value="&quot;It is in the hold, perhaps in one of those boxes. I'll unscrew them one by one and see. You work the helm.&quot;"/><property name="Power" value="4"/><property name="Toughness" value="4"/><property name="PT Box" value="4 / 4"/><property name="Artist" value="Lucas Graciano"/><property name="MultiverseId" value="SF-VOW_341a"/><property name="Number" value="341"/></card><card id="e43105e3-5d19-4bc8-802f-f983251332b1" name="Edgar Markov's Coffin"><property name="Cost" value=""/><property name="Converted Mana Cost" value="4"/><property name="Color" value="Multicolor White Black"/><property name="Type" value="Legendary Artifact"/><property name="Subtype" value=""/><property name="Rarity" value="Rare"/><property name="Rules" value="At the beginning of your upkeep, create a 1/1 white and black Vampire creature token with lifelink and put a bloodline counter on Edgar Markov's Coffin. Then if there are three or more bloodline counters on it, remove those counters and transform it."/><property name="Flavor" value=""/><property name="Power" value=""/><property name="Toughness" value=""/><property name="PT Box" value=""/><property name="Artist" value="Lucas Graciano"/><property name="MultiverseId" value="SF-VOW_341b"/><property name="Number" value="341"/></card><card id="ad87a5b3-d6cf-4200-a42d-ff038936a964" name="Faithbound Judge"><property name="Cost" value="{1}{W}{W}"/><property name="Converted Mana Cost" value="3"/><property name="Color" value="White"/><property name="Type" value="Creature"/><property name="Subtype" value="Spirit Soldier"/><property name="Rarity" value="Mythic Rare"/><property name="Rules" value="Defender, flying, vigilance&#xD;&#xA;At the beginning of your upkeep, if Faithbound Judge has two or fewer judgment counters on it, put a judgment counter on it.&#xD;&#xA;As long as Faithbound Judge has three or more judgment counters on it, it can attack as though it didn't have defender.&#xD;&#xA;Disturb {5}{W}{W}"/><property name="Flavor" value=""/><property name="Power" value="4"/><property name="Toughness" value="4"/><property name="PT Box" value="4 / 4"/><property name="Artist" value="Svetlin Velinov"/><property name="MultiverseId" value="SF-VOW_348a"/><property name="Number" value="348"/></card><card id="ae3c95f2-0a68-4cfc-978b-3cd7a0125b41" name="Sinner's Judgment"><property name="Cost" value=""/><property name="Converted Mana Cost" value="3"/><property name="Color" value="White"/><property name="Type" value="Enchantment"/><property name="Subtype" value="Aura Curse"/><property name="Rarity" value="Mythic Rare"/><property name="Rules" value="Enchant player&#xD;&#xA;At the beginning of your upkeep, put a judgment counter on Sinner's Judgment. Then if there are three or more judgment counters on it, enchanted player loses the game.&#xD;&#xA;If Sinner's Judgment would be put into a graveyard from anywhere, exile it instead."/><property name="Flavor" value=""/><property name="Power" value=""/><property name="Toughness" value=""/><property name="PT Box" value=""/><property name="Artist" value="Svetlin Velinov"/><property name="MultiverseId" value="SF-VOW_348b"/><property name="Number" value="348"/></card><card id="560e4f1c-e7a4-4b22-b7d0-ba0c6d9c383f" name="Wedding Announcement"><property name="Cost" value="{2}{W}"/><property name="Converted Mana Cost" value="3"/><property name="Color" value="White"/><property name="Type" value="Enchantment"/><property name="Subtype" value=""/><property name="Rarity" value="Rare"/><property name="Rules" value="At the beginning of your end step, put an invitation counter on Wedding Announcement. If you attacked with two or more creatures this turn, draw a card. Otherwise, create a 1/1 white Human creature token. Then if Wedding Announcement has three or more invitation counters on it, transform it."/><property name="Flavor" value=""/><property name="Power" value=""/><property name="Toughness" value=""/><property name="PT Box" value=""/><property name="Artist" value="Caroline Gariba"/><property name="MultiverseId" value="SF-VOW_355a"/><property name="Number" value="355"/></card><card id="229d56e7-5d46-458f-8364-12e96196e0d7" name="Wedding Festivity"><property name="Cost" value=""/><property name="Converted Mana Cost" value="3"/><property name="Color" value="White"/><property name="Type" value="Enchantment"/><property name="Subtype" value=""/><property name="Rarity" value="Rare"/><property name="Rules" value="Creatures you control get +1/+1."/><property name="Flavor" value=""/><property name="Power" value=""/><property name="Toughness" value=""/><property name="PT Box" value=""/><property name="Artist" value="Caroline Gariba"/><property name="MultiverseId" value="SF-VOW_355b"/><property name="Number" value="355"/></card><card id="58dabe99-adda-4928-bcd9-9946343bbf80" name="Mirrorhall Mimic"><property name="Cost" value="{3}{U}"/><property name="Converted Mana Cost" value="4"/><property name="Color" value="Blue"/><property name="Type" value="Creature"/><property name="Subtype" value="Spirit"/><property name="Rarity" value="Rare"/><property name="Rules" value="You may have Mirrorhall Mimic enter the battlefield as a copy of any creature on the battlefield, except it's a Spirit in addition to its other types.&#xD;&#xA;Disturb {3}{U}{U} (You may cast this card from your graveyard transformed for its disturb cost.)"/><property name="Flavor" value=""/><property name="Power" value="0"/><property name="Toughness" value="0"/><property name="PT Box" value="0 / 0"/><property name="Artist" value="Justine Cruz"/><property name="MultiverseId" value="SF-VOW_361a"/><property name="Number" value="361"/></card><card id="0b2d2b9c-6ac9-4632-8524-38abcb16dae1" name="Ghastly Mimicry"><property name="Cost" value=""/><property name="Converted Mana Cost" value="4"/><property name="Color" value="Blue"/><property name="Type" value="Enchantment"/><property name="Subtype" value="Aura"/><property name="Rarity" value="Rare"/><property name="Rules" value="Enchant creature&#xD;&#xA;At the beginning of your upkeep, create a token that's a copy of enchanted creature, except it's a Spirit in addition to its other types.&#xD;&#xA;If Ghastly Mimicry would be put into a graveyard from anywhere, exile it instead."/><property name="Flavor" value=""/><property name="Power" value=""/><property name="Toughness" value=""/><property name="PT Box" value=""/><property name="Artist" value="Justine Cruz"/><property name="MultiverseId" value="SF-VOW_361b"/><property name="Number" value="361"/></card><card id="3206bfde-732d-4b06-b616-6d73aacc1478" name="Concealing Curtains"><property name="Cost" value="{B}"/><property name="Converted Mana Cost" value="1"/><property name="Color" value="Black"/><property name="Type" value="Creature"/><property name="Subtype" value="Wall"/><property name="Rarity" value="Rare"/><property name="Rules" value="Defender&#xD;&#xA;{2}{B}: Transform Concealing Curtains. Activate only as a sorcery."/><property name="Flavor" value=""/><property name="Power" value="0"/><property name="Toughness" value="4"/><property name="PT Box" value="0 / 4"/><property name="Artist" value="Brian Valeza"/><property name="MultiverseId" value="SF-VOW_367a"/><property name="Number" value="367"/></card><card id="af93770b-91c4-487f-873a-a463b8936026" name="Revealing Eye"><property name="Cost" value=""/><property name="Converted Mana Cost" value="1"/><property name="Color" value="Black"/><property name="Type" value="Creature"/><property name="Subtype" value="Eye Horror"/><property name="Rarity" value="Rare"/><property name="Rules" value="Menace&#xD;&#xA;When this creature transforms into Revealing Eye, target opponent reveals their hand. You may choose a nonland card from it. If you do, that player discards that card, then draws a card."/><property name="Flavor" value=""/><property name="Power" value="3"/><property name="Toughness" value="4"/><property name="PT Box" value="3 / 4"/><property name="Artist" value="Brian Valeza"/><property name="MultiverseId" value="SF-VOW_367b"/><property name="Number" value="367"/></card><card id="52caaeb1-02b1-450a-8ab8-3d8f8ec43ab3" name="Ill-Tempered Loner"><property name="Cost" value="{2}{R}{R}"/><property name="Converted Mana Cost" value="4"/><property name="Color" value="Red"/><property name="Type" value="Creature"/><property name="Subtype" value="Human Werewolf"/><property name="Rarity" value="Rare"/><property name="Rules" value="Whenever Ill-Tempered Loner is dealt damage, it deals that much damage to any target.&#xD;&#xA;{1}{R}: Ill-Tempered Loner gets +2/+0 until end of turn.&#xD;&#xA;Daybound (If a player casts no spells during their own turn, it becomes night next turn.)"/><property name="Flavor" value=""/><property name="Power" value="3"/><property name="Toughness" value="3"/><property name="PT Box" value="3 / 3"/><property name="Artist" value="Grzegorz Rutkowski"/><property name="MultiverseId" value="SF-VOW_378a"/><property name="Number" value="378"/></card><card id="e33abe42-6d65-4b0e-976b-1633d2385005" name="Howlpack Avenger"><property name="Cost" value=""/><property name="Converted Mana Cost" value="4"/><property name="Color" value="Red"/><property name="Type" value="Creature"/><property name="Subtype" value="Werewolf"/><property name="Rarity" value="Rare"/><property name="Rules" value="Whenever a permanent you control is dealt damage, Howlpack Avenger deals that much damage to any target.&#xD;&#xA;{1}{R}: Howlpack Avenger gets +2/+0 until end of turn.&#xD;&#xA;Nightbound (If a player casts at least two spells during their own turn, it becomes day next turn.)"/><property name="Flavor" value=""/><property name="Power" value="4"/><property name="Toughness" value="4"/><property name="PT Box" value="4 / 4"/><property name="Artist" value="Grzegorz Rutkowski"/><property name="MultiverseId" value="SF-VOW_378b"/><property name="Number" value="378"/></card><card id="a6b12b63-1ead-47e5-8da2-95edde344e85" name="Volatile Arsonist"><property name="Cost" value="{3}{R}{R}"/><property name="Converted Mana Cost" value="5"/><property name="Color" value="Red"/><property name="Type" value="Creature"/><property name="Subtype" value="Human Werewolf"/><property name="Rarity" value="Mythic Rare"/><property name="Rules" value="Menace, haste&#xD;&#xA;Whenever Volatile Arsonist attacks, it deals 1 damage to each of up to one target creature, up to one target player, and/or up to one target planeswalker.&#xD;&#xA;Daybound (If a player casts no spells during their own turn, it becomes night next turn.)"/><property name="Flavor" value=""/><property name="Power" value="4"/><property name="Toughness" value="4"/><property name="PT Box" value="4 / 4"/><property name="Artist" value="Gabor Szikszai"/><property name="MultiverseId" value="SF-VOW_382a"/><property name="Number" value="382"/></card><card id="c8810621-2671-4e4e-8c68-a2c5172dc0b7" name="Dire-Strain Anarchist"><property name="Cost" value=""/><property name="Converted Mana Cost" value="5"/><property name="Color" value="Red"/><property name="Type" value="Creature"/><property name="Subtype" value="Werewolf"/><property name="Rarity" value="Mythic Rare"/><property name="Rules" value="Menace, haste&#xD;&#xA;Whenever Dire-Strain Anarchist attacks, it deals 2 damage to each of up to one target creature, up to one target player, and/or up to one target planeswalker.&#xD;&#xA;Nightbound (If a player casts at least two spells during their own turn, it becomes day next turn.)"/><property name="Flavor" value=""/><property name="Power" value="5"/><property name="Toughness" value="5"/><property name="PT Box" value="5 / 5"/><property name="Artist" value="Gabor Szikszai"/><property name="MultiverseId" value="SF-VOW_382b"/><property name="Number" value="382"/></card><card id="8035d0c9-a35b-4a89-8291-59b377ce3436" name="Avabruck Caretaker"><property name="Cost" value="{4}{G}{G}"/><property name="Converted Mana Cost" value="6"/><property name="Color" value="Green"/><property name="Type" value="Creature"/><property name="Subtype" value="Human Werewolf"/><property name="Rarity" value="Mythic Rare"/><property name="Rules" value="Hexproof&#xD;&#xA;At the beginning of combat on your turn, put two +1/+1 counters on another target creature you control.&#xD;&#xA;Daybound (If a player casts no spells during their own turn, it becomes night next turn.)"/><property name="Flavor" value=""/><property name="Power" value="4"/><property name="Toughness" value="4"/><property name="PT Box" value="4 / 4"/><property name="Artist" value="Heonhwa Choe"/><property name="MultiverseId" value="SF-VOW_384a"/><property name="Number" value="384"/></card><card id="8a7c20a1-5bcc-4eff-a227-fe86d3731247" name="Hollowhenge Huntmaster"><property name="Cost" value=""/><property name="Converted Mana Cost" value="6"/><property name="Color" value="Green"/><property name="Type" value="Creature"/><property name="Subtype" value="Werewolf"/><property name="Rarity" value="Mythic Rare"/><property name="Rules" value="Hexproof&#xD;&#xA;Other permanents you control have hexproof.&#xD;&#xA;At the beginning of combat on your turn, put two +1/+1 counters on each creature you control.&#xD;&#xA;Nightbound (If a player casts at least two spells during their own turn, it becomes day next turn.)"/><property name="Flavor" value=""/><property name="Power" value="6"/><property name="Toughness" value="6"/><property name="PT Box" value="6 / 6"/><property name="Artist" value="Heonhwa Choe"/><property name="MultiverseId" value="SF-VOW_384b"/><property name="Number" value="384"/></card><card id="dc610cd3-dc58-4f11-91af-a8f4faf3c4d6" name="Howlpack Piper"><property name="Cost" value="{3}{G}"/><property name="Converted Mana Cost" value="4"/><property name="Color" value="Green"/><property name="Type" value="Creature"/><property name="Subtype" value="Human Werewolf"/><property name="Rarity" value="Rare"/><property name="Rules" value="This spell can't be countered.&#xD;&#xA;{1}{G}, {T}: You may put a creature card from your hand onto the battlefield. If it's a Wolf or Werewolf, untap Howlpack Piper. Activate only as a sorcery.&#xD;&#xA;Daybound (If a player casts no spells during their own turn, it becomes night next turn.)"/><property name="Flavor" value=""/><property name="Power" value="2"/><property name="Toughness" value="2"/><property name="PT Box" value="2 / 2"/><property name="Artist" value="Cristi Balanescu"/><property name="MultiverseId" value="SF-VOW_392a"/><property name="Number" value="392"/></card><card id="dfa0c298-a8b4-4fed-bc44-7f59f0cf9943" name="Wildsong Howler"><property name="Cost" value=""/><property name="Converted Mana Cost" value="4"/><property name="Color" value="Green"/><property name="Type" value="Creature"/><property name="Subtype" value="Werewolf"/><property name="Rarity" value="Rare"/><property name="Rules" value="Whenever this creature enters the battlefield or transforms into Wildsong Howler, look at the top six cards of your library. You may reveal a creature card from among them and put it into your hand. Put the rest on the bottom of your library in a random order.&#xD;&#xA;Nightbound (If a player casts at least two spells during their own turn, it becomes day next turn.)"/><property name="Flavor" value=""/><property name="Power" value="4"/><property name="Toughness" value="4"/><property name="PT Box" value="4 / 4"/><property name="Artist" value="Cristi Balanescu"/><property name="MultiverseId" value="SF-VOW_392b"/><property name="Number" value="392"/></card><card id="4c4811dd-5883-43dc-881a-efad9a3a7463" name="Ulvenwald Oddity"><property name="Cost" value="{2}{G}{G}"/><property name="Converted Mana Cost" value="4"/><property name="Color" value="Green"/><property name="Type" value="Creature"/><property name="Subtype" value="Beast"/><property name="Rarity" value="Rare"/><property name="Rules" value="Trample, haste&#xD;&#xA;{5}{G}{G}: Transform Ulvenwald Oddity."/><property name="Flavor" value=""/><property name="Power" value="4"/><property name="Toughness" value="4"/><property name="PT Box" value="4 / 4"/><property name="Artist" value="Brent Hollowell"/><property name="MultiverseId" value="SF-VOW_394a"/><property name="Number" value="394"/></card><card id="78cc05f6-dc5e-49bc-9216-238392f2ced8" name="Ulvenwald Behemoth"><property name="Cost" value=""/><property name="Converted Mana Cost" value="4"/><property name="Color" value="Green"/><property name="Type" value="Creature"/><property name="Subtype" value="Beast Horror"/><property name="Rarity" value="Rare"/><property name="Rules" value="Trample, haste&#xD;&#xA;Other creatures you control get +1/+1 and have trample and haste."/><property name="Flavor" value=""/><property name="Power" value="8"/><property name="Toughness" value="8"/><property name="PT Box" value="8 / 8"/><property name="Artist" value="Brent Hollowell"/><property name="MultiverseId" value="SF-VOW_394b"/><property name="Number" value="394"/></card></cards></set>