<?xml version="1.0" encoding="utf-8" standalone="yes"?><set name="Unfinity Attractions" id="C94B2C89-9CDB-4789-9602-D582C9BDB6FE" gameId="A6C8D2E8-7CD8-11DD-8F94-E62B56D89593" gameVersion="2.0.4" version="3.1"><packaging></packaging><cards><card id="b18f01cb-1e9b-4e29-b6da-ceba3537e7fc" name="Spinny Ride"><property name="Cost" value=""/><property name="Converted Mana Cost" value="0"/><property name="Color" value="Colorless"/><property name="Type" value="Artifact"/><property name="Subtype" value="Attraction"/><property name="Rarity" value="Common"/><property name="Rules" value="Visit - Tap target creature an opponent controls.&#xD;&#xA;Lights - 2, 3, 6"/><property name="Flavor" value="&quot;If a species will pay to be moved in a circle, I will find a way to let it.&quot;&#xD;&#xA; - Myra the Magnificent"/><property name="Power" value=""/><property name="Toughness" value=""/><property name="PT Box" value=""/><property name="Artist" value="Aaron J. Riley"/><property name="MultiverseId" value="SF-UNF_227e"/><property name="Number" value="227e"/></card><card id="e3e65329-32a9-4c97-9d54-ca0830142b7a" name="Spinny Ride"><property name="Cost" value=""/><property name="Converted Mana Cost" value="0"/><property name="Color" value="Colorless"/><property name="Type" value="Artifact"/><property name="Subtype" value="Attraction"/><property name="Rarity" value="Common"/><property name="Rules" value="Visit - Tap target creature an opponent controls.&#xD;&#xA;Lights - 2, 3, 6"/><property name="Flavor" value="The maximum recommended speed warning system snapped off years ago, but they hadn't encountered problems yet."/><property name="Power" value=""/><property name="Toughness" value=""/><property name="PT Box" value=""/><property name="Artist" value="Aaron J. Riley"/><property name="MultiverseId" value="SF-UNF_227f"/><property name="Number" value="227f"/></card><card id="6f3355eb-b841-4991-8950-c177d82971f6" name="Hall of Mirrors"><property name="Cost" value=""/><property name="Converted Mana Cost" value="0"/><property name="Color" value="Colorless"/><property name="Type" value="Artifact"/><property name="Subtype" value="Attraction"/><property name="Rarity" value="Rare"/><property name="Rules" value="Visit - Choose target creature you control. Each other creature you control becomes a copy of that creature until end of turn, except it isn't legendary.&#xD;&#xA;Lights - 2, 6"/><property name="Flavor" value="For a smaller fee, you can pop in quickly to try on a pair of jeans."/><property name="Power" value=""/><property name="Toughness" value=""/><property name="PT Box" value=""/><property name="Artist" value="Vincent Christiaens"/><property name="MultiverseId" value="SF-UNF_216b"/><property name="Number" value="216"/></card></cards></set>